parsing_helper/__init__.py
parsing_helper/admin.py
parsing_helper/logger.py
parsing_helper/models.py
parsing_helper/secret_keeper.py
parsing_helper/settings.py
parsing_helper/django_commands/__init__.py
parsing_helper/django_commands/create_admin.py
parsing_helper/django_commands/django_command.py
parsing_helper/pages/__init__.py
parsing_helper/pages/base_page.py
parsing_helper/web_elements/__init__.py
parsing_helper/web_elements/collection.py
parsing_helper/web_elements/element.py
parsing_helper-0.0.18.data/data/project_data.json
parsing_helper-0.0.18.data/data/requirements.txt
parsing_helper-0.0.18.dist-info/METADATA
parsing_helper-0.0.18.dist-info/WHEEL
parsing_helper-0.0.18.dist-info/top_level.txt
parsing_helper-0.0.18.dist-info/RECORD
